hyperborea/__init__.py
hyperborea/dark_mode.py
hyperborea/device_info_dialog.py
hyperborea/download.py
hyperborea/event_database.py
hyperborea/namedprocess.py
hyperborea/preferences.py
hyperborea/py.typed
hyperborea/ringbuffer.py
hyperborea/setting_widget.py
hyperborea/test_ringbuffer.py
hyperborea/unit_formatter_spinbox.py
hyperborea/unit_preferences.py
hyperborea/unit_selection_dialog.py
hyperborea/version.py
hyperborea/ui/__init__.py
hyperborea/ui/ui_device_info_dialog.py
hyperborea/ui/ui_unit_preferences_widget.py
hyperborea/ui/ui_unit_selection_dialog.py
hyperborea-2.1.0.dist-info/licenses/LICENSE.txt
hyperborea-2.1.0.dist-info/METADATA
hyperborea-2.1.0.dist-info/WHEEL
hyperborea-2.1.0.dist-info/top_level.txt
hyperborea-2.1.0.dist-info/RECORD
