Metadata-Version: 2.4
Name: hyperborea
Version: 2.1.0
Summary: Utility library for streaming from Asphodel devices
Author-email: Suprock Technologies <inquiries@suprocktech.com>
License-Expression: ISC
Project-URL: Repository, https://bitbucket.org/suprocktech/hyperborea
Keywords: asphodel,suprock,apd
Requires-Python: >=3.10
License-File: LICENSE.txt
Requires-Dist: asphodel>=2.0.0
Requires-Dist: numpy
Requires-Dist: PySide6-Essentials
Requires-Dist: requests
Requires-Dist: setproctitle
Dynamic: license-file
